sspi/__init__.py
sspi/_credential.py
sspi/_filetime.py
sspi/_sec_context.py
sspi/py.typed
sspi/raw/__init__.py
sspi/raw/_context_attributes.cp310-win_amd64.pyd
sspi/raw/_context_attributes.pyi
sspi/raw/_credential.cp310-win_amd64.pyd
sspi/raw/_credential.pyi
sspi/raw/_credential_attributes.cp310-win_amd64.pyd
sspi/raw/_credential_attributes.pyi
sspi/raw/_message.cp310-win_amd64.pyd
sspi/raw/_message.pyi
sspi/raw/_ntstatus.cp310-win_amd64.pyd
sspi/raw/_ntstatus.pyi
sspi/raw/_security_buffer.cp310-win_amd64.pyd
sspi/raw/_security_buffer.pyi
sspi/raw/_security_context.cp310-win_amd64.pyd
sspi/raw/_security_context.pyi
sspi/raw/_security_package.cp310-win_amd64.pyd
sspi/raw/_security_package.pyi
sspi/raw/_text.cp310-win_amd64.pyd
sspi/raw/_winerror.py
sspi-0.1.0.dist-info/LICENSE
sspi-0.1.0.dist-info/METADATA
sspi-0.1.0.dist-info/WHEEL
sspi-0.1.0.dist-info/top_level.txt
sspi-0.1.0.dist-info/RECORD
