Metadata-Version: 2.1
Name: sspi
Version: 0.1.0
Summary: SSPI API bindings for Python
Author-email: Jordan Borean <jborean93@gmail.com>
License: MIT License
Project-URL: homepage, https://github.com/jborean93/pysspi
Keywords: sspi,kerberos,negotiate
Classifier: Development Status :: 4 - Beta
Classifier: License :: OSI Approved :: MIT License
Classifier: Programming Language :: Python :: 3
Classifier: Programming Language :: Python :: 3.8
Classifier: Programming Language :: Python :: 3.9
Classifier: Programming Language :: Python :: 3.10
Classifier: Programming Language :: Python :: 3.11
Classifier: Programming Language :: Python :: 3.12
Requires-Python: >=3.8
License-File: LICENSE
